vallaris/__init__.py
vallaris/perform.py
vallaris/utils.py
vallaris-1.5.7.dist-info/LICENSE.txt
vallaris-1.5.7.dist-info/METADATA
vallaris-1.5.7.dist-info/WHEEL
vallaris-1.5.7.dist-info/top_level.txt
vallaris-1.5.7.dist-info/RECORD
