Metadata-Version: 2.1
Name: vallaris
Version: 1.5.7
Summary: A package to processing Vallaris Maps
Home-page: https://v2k.vallarismaps.com
Author: Sattawat Arab
Author-email: support@vallarismaps.com
License: UNKNOWN
Platform: UNKNOWN
Classifier: Programming Language :: Python :: 3
Classifier: License :: OSI Approved :: MIT License
Classifier: Operating System :: OS Independent
Requires-Python: >=3.6
Requires-Dist: earthpy
Requires-Dist: geojson
Requires-Dist: geopandas
Requires-Dist: jsonschema
Requires-Dist: matplotlib
Requires-Dist: ndjson
Requires-Dist: numpy
Requires-Dist: pandas
Requires-Dist: python-dotenv
Requires-Dist: requests
Requires-Dist: rtree
Requires-Dist: shapely
Requires-Dist: tqdm
Requires-Dist: uuid
